wirepas_positioning_messaging/__about__.py
wirepas_positioning_messaging/__init__.py
wirepas_positioning_messaging/__main__.py
wirepas_positioning_messaging/proto/__init__.py
wirepas_positioning_messaging/proto/public_pb2.py
wirepas_positioning_messaging/proto/public_pb2_grpc.py
wirepas_positioning_messaging-1.7.1.dist-info/LICENSE
wirepas_positioning_messaging-1.7.1.dist-info/METADATA
wirepas_positioning_messaging-1.7.1.dist-info/WHEEL
wirepas_positioning_messaging-1.7.1.dist-info/top_level.txt
wirepas_positioning_messaging-1.7.1.dist-info/RECORD
