Metadata-Version: 2.1
Name: wirepas-positioning-messaging
Version: 1.7.1
Summary: WPE protocol buffers bindings.
Home-page: https://github.com/wirepas/wirepas-positioning-messaging-python
Author: Wirepas Ltd
Author-email: opensource@wirepas.com
License: Apache-2
Keywords: wirepas WPE
Classifier: Development Status :: 5 - Production/Stable
Classifier: Intended Audience :: Developers
Classifier: License :: OSI Approved :: Apache Software License
Classifier: Topic :: Software Development :: Libraries
Classifier: Programming Language :: Python :: 3
License-File: LICENSE
Requires-Dist: grpcio-tools ==1.46.5
